{
  "images": [
    {
      "id": 1,
      "publicId": "10_x1vaoi",
      "src": "https://res.cloudinary.com/dwerrhasa/image/upload/f_auto,q_auto,w_800/10_x1vaoi",
      "title": "10_x1vaoi"
    },
    {
      "id": 2,
      "publicId": "Title_Page_fxmi6h",
      "src": "https://res.cloudinary.com/dwerrhasa/image/upload/f_auto,q_auto,w_800/Title_Page_fxmi6h",
      "title": "Title_Page_fxmi6h"
    },
    {
      "id": 3,
      "publicId": "Cover_Page_qoi9fq",
      "src": "https://res.cloudinary.com/dwerrhasa/image/upload/f_auto,q_auto,w_800/Cover_Page_qoi9fq",
      "title": "Cover_Page_qoi9fq"
    },
    {
      "id": 4,
      "publicId": "Zapravo_17_osvylt",
      "src": "https://res.cloudinary.com/dwerrhasa/image/upload/f_auto,q_auto,w_800/Zapravo_17_osvylt",
      "title": "Zapravo_17_osvylt"
    },
    {
      "id": 5,
      "publicId": "26_ehkbfs",
      "src": "https://res.cloudinary.com/dwerrhasa/image/upload/f_auto,q_auto,w_800/26_ehkbfs",
      "title": "26_ehkbfs"
    },
    {
      "id": 6,
      "publicId": "Treca_a35nwh",
      "src": "https://res.cloudinary.com/dwerrhasa/image/upload/f_auto,q_auto,w_800/Treca_a35nwh",
      "title": "Treca_a35nwh"
    },
    {
      "id": 7,
      "publicId": "Copyright_Page_bunnow",
      "src": "https://res.cloudinary.com/dwerrhasa/image/upload/f_auto,q_auto,w_800/Copyright_Page_bunnow",
      "title": "Copyright_Page_bunnow"
    },
    {
      "id": 8,
      "publicId": "23_bblycq",
      "src": "https://res.cloudinary.com/dwerrhasa/image/upload/f_auto,q_auto,w_800/23_bblycq",
      "title": "23_bblycq"
    },
    {
      "id": 9,
      "publicId": "8.JPG_fgl7lp",
      "src": "https://res.cloudinary.com/dwerrhasa/image/upload/f_auto,q_auto,w_800/8.JPG_fgl7lp",
      "title": "8.JPG_fgl7lp"
    },
    {
      "id": 10,
      "publicId": "Image46_lmkdta",
      "src": "https://res.cloudinary.com/dwerrhasa/image/upload/f_auto,q_auto,w_800/Image46_lmkdta",
      "title": "Image46_lmkdta"
    },
    {
      "id": 11,
      "publicId": "Image45_pgguhp",
      "src": "https://res.cloudinary.com/dwerrhasa/image/upload/f_auto,q_auto,w_800/Image45_pgguhp",
      "title": "Image45_pgguhp"
    },
    {
      "id": 12,
      "publicId": "Image38_kklaez",
      "src": "https://res.cloudinary.com/dwerrhasa/image/upload/f_auto,q_auto,w_800/Image38_kklaez",
      "title": "Image38_kklaez"
    },
    {
      "id": 13,
      "publicId": "Image42_auhpsp",
      "src": "https://res.cloudinary.com/dwerrhasa/image/upload/f_auto,q_auto,w_800/Image42_auhpsp",
      "title": "Image42_auhpsp"
    },
    {
      "id": 14,
      "publicId": "Image44_xnxnt7",
      "src": "https://res.cloudinary.com/dwerrhasa/image/upload/f_auto,q_auto,w_800/Image44_xnxnt7",
      "title": "Image44_xnxnt7"
    },
    {
      "id": 15,
      "publicId": "Image37_lspei2",
      "src": "https://res.cloudinary.com/dwerrhasa/image/upload/f_auto,q_auto,w_800/Image37_lspei2",
      "title": "Image37_lspei2"
    },
    {
      "id": 16,
      "publicId": "Image43_mzm7yn",
      "src": "https://res.cloudinary.com/dwerrhasa/image/upload/f_auto,q_auto,w_800/Image43_mzm7yn",
      "title": "Image43_mzm7yn"
    },
    {
      "id": 17,
      "publicId": "Image41_fmlqoq",
      "src": "https://res.cloudinary.com/dwerrhasa/image/upload/f_auto,q_auto,w_800/Image41_fmlqoq",
      "title": "Image41_fmlqoq"
    },
    {
      "id": 18,
      "publicId": "Image34_qiod25",
      "src": "https://res.cloudinary.com/dwerrhasa/image/upload/f_auto,q_auto,w_800/Image34_qiod25",
      "title": "Image34_qiod25"
    },
    {
      "id": 19,
      "publicId": "Image40_hjsgkc",
      "src": "https://res.cloudinary.com/dwerrhasa/image/upload/f_auto,q_auto,w_800/Image40_hjsgkc",
      "title": "Image40_hjsgkc"
    },
    {
      "id": 20,
      "publicId": "Image39_fj62zd",
      "src": "https://res.cloudinary.com/dwerrhasa/image/upload/f_auto,q_auto,w_800/Image39_fj62zd",
      "title": "Image39_fj62zd"
    },
    {
      "id": 21,
      "publicId": "Image36_oa4k5n",
      "src": "https://res.cloudinary.com/dwerrhasa/image/upload/f_auto,q_auto,w_800/Image36_oa4k5n",
      "title": "Image36_oa4k5n"
    },
    {
      "id": 22,
      "publicId": "Image33_ntrqou",
      "src": "https://res.cloudinary.com/dwerrhasa/image/upload/f_auto,q_auto,w_800/Image33_ntrqou",
      "title": "Image33_ntrqou"
    },
    {
      "id": 23,
      "publicId": "Image35_th279i",
      "src": "https://res.cloudinary.com/dwerrhasa/image/upload/f_auto,q_auto,w_800/Image35_th279i",
      "title": "Image35_th279i"
    },
    {
      "id": 24,
      "publicId": "Image32_t5wrzo",
      "src": "https://res.cloudinary.com/dwerrhasa/image/upload/f_auto,q_auto,w_800/Image32_t5wrzo",
      "title": "Image32_t5wrzo"
    },
    {
      "id": 25,
      "publicId": "Image31_k7q9ho",
      "src": "https://res.cloudinary.com/dwerrhasa/image/upload/f_auto,q_auto,w_800/Image31_k7q9ho",
      "title": "Image31_k7q9ho"
    },
    {
      "id": 26,
      "publicId": "Image30_fzsaxs",
      "src": "https://res.cloudinary.com/dwerrhasa/image/upload/f_auto,q_auto,w_800/Image30_fzsaxs",
      "title": "Image30_fzsaxs"
    },
    {
      "id": 27,
      "publicId": "Image29_i3s9qg",
      "src": "https://res.cloudinary.com/dwerrhasa/image/upload/f_auto,q_auto,w_800/Image29_i3s9qg",
      "title": "Image29_i3s9qg"
    },
    {
      "id": 28,
      "publicId": "Image28_pklyzm",
      "src": "https://res.cloudinary.com/dwerrhasa/image/upload/f_auto,q_auto,w_800/Image28_pklyzm",
      "title": "Image28_pklyzm"
    },
    {
      "id": 29,
      "publicId": "Image27_ybuq47",
      "src": "https://res.cloudinary.com/dwerrhasa/image/upload/f_auto,q_auto,w_800/Image27_ybuq47",
      "title": "Image27_ybuq47"
    },
    {
      "id": 30,
      "publicId": "Image26_ruo4dl",
      "src": "https://res.cloudinary.com/dwerrhasa/image/upload/f_auto,q_auto,w_800/Image26_ruo4dl",
      "title": "Image26_ruo4dl"
    },
    {
      "id": 31,
      "publicId": "Image25_z7y4i5",
      "src": "https://res.cloudinary.com/dwerrhasa/image/upload/f_auto,q_auto,w_800/Image25_z7y4i5",
      "title": "Image25_z7y4i5"
    },
    {
      "id": 32,
      "publicId": "Image24_bqtptn",
      "src": "https://res.cloudinary.com/dwerrhasa/image/upload/f_auto,q_auto,w_800/Image24_bqtptn",
      "title": "Image24_bqtptn"
    },
    {
      "id": 33,
      "publicId": "Image23_uoyggt",
      "src": "https://res.cloudinary.com/dwerrhasa/image/upload/f_auto,q_auto,w_800/Image23_uoyggt",
      "title": "Image23_uoyggt"
    },
    {
      "id": 34,
      "publicId": "Image22_chqd04",
      "src": "https://res.cloudinary.com/dwerrhasa/image/upload/f_auto,q_auto,w_800/Image22_chqd04",
      "title": "Image22_chqd04"
    },
    {
      "id": 35,
      "publicId": "Image21_e03dc1",
      "src": "https://res.cloudinary.com/dwerrhasa/image/upload/f_auto,q_auto,w_800/Image21_e03dc1",
      "title": "Image21_e03dc1"
    },
    {
      "id": 36,
      "publicId": "Image18_yxhylb",
      "src": "https://res.cloudinary.com/dwerrhasa/image/upload/f_auto,q_auto,w_800/Image18_yxhylb",
      "title": "Image18_yxhylb"
    },
    {
      "id": 37,
      "publicId": "Image20_p6w2sw",
      "src": "https://res.cloudinary.com/dwerrhasa/image/upload/f_auto,q_auto,w_800/Image20_p6w2sw",
      "title": "Image20_p6w2sw"
    },
    {
      "id": 38,
      "publicId": "Image19_beflfm",
      "src": "https://res.cloudinary.com/dwerrhasa/image/upload/f_auto,q_auto,w_800/Image19_beflfm",
      "title": "Image19_beflfm"
    },
    {
      "id": 39,
      "publicId": "Image17_kjnr4m",
      "src": "https://res.cloudinary.com/dwerrhasa/image/upload/f_auto,q_auto,w_800/Image17_kjnr4m",
      "title": "Image17_kjnr4m"
    },
    {
      "id": 40,
      "publicId": "Image16_miu7ev",
      "src": "https://res.cloudinary.com/dwerrhasa/image/upload/f_auto,q_auto,w_800/Image16_miu7ev",
      "title": "Image16_miu7ev"
    },
    {
      "id": 41,
      "publicId": "Image11_n5keih",
      "src": "https://res.cloudinary.com/dwerrhasa/image/upload/f_auto,q_auto,w_800/Image11_n5keih",
      "title": "Image11_n5keih"
    },
    {
      "id": 42,
      "publicId": "Image3_whreko",
      "src": "https://res.cloudinary.com/dwerrhasa/image/upload/f_auto,q_auto,w_800/Image3_whreko",
      "title": "Image3_whreko"
    },
    {
      "id": 43,
      "publicId": "Image15_zopfei",
      "src": "https://res.cloudinary.com/dwerrhasa/image/upload/f_auto,q_auto,w_800/Image15_zopfei",
      "title": "Image15_zopfei"
    },
    {
      "id": 44,
      "publicId": "Image14_ycsoic",
      "src": "https://res.cloudinary.com/dwerrhasa/image/upload/f_auto,q_auto,w_800/Image14_ycsoic",
      "title": "Image14_ycsoic"
    },
    {
      "id": 45,
      "publicId": "Image13_y0iqot",
      "src": "https://res.cloudinary.com/dwerrhasa/image/upload/f_auto,q_auto,w_800/Image13_y0iqot",
      "title": "Image13_y0iqot"
    },
    {
      "id": 46,
      "publicId": "Image12_zkvwsx",
      "src": "https://res.cloudinary.com/dwerrhasa/image/upload/f_auto,q_auto,w_800/Image12_zkvwsx",
      "title": "Image12_zkvwsx"
    },
    {
      "id": 47,
      "publicId": "Image10_b3bjso",
      "src": "https://res.cloudinary.com/dwerrhasa/image/upload/f_auto,q_auto,w_800/Image10_b3bjso",
      "title": "Image10_b3bjso"
    },
    {
      "id": 48,
      "publicId": "Image9_xujcbz",
      "src": "https://res.cloudinary.com/dwerrhasa/image/upload/f_auto,q_auto,w_800/Image9_xujcbz",
      "title": "Image9_xujcbz"
    },
    {
      "id": 49,
      "publicId": "Image7_xcqj2w",
      "src": "https://res.cloudinary.com/dwerrhasa/image/upload/f_auto,q_auto,w_800/Image7_xcqj2w",
      "title": "Image7_xcqj2w"
    },
    {
      "id": 50,
      "publicId": "Image6_dutfs1",
      "src": "https://res.cloudinary.com/dwerrhasa/image/upload/f_auto,q_auto,w_800/Image6_dutfs1",
      "title": "Image6_dutfs1"
    },
    {
      "id": 51,
      "publicId": "Image4_glkjwo",
      "src": "https://res.cloudinary.com/dwerrhasa/image/upload/f_auto,q_auto,w_800/Image4_glkjwo",
      "title": "Image4_glkjwo"
    },
    {
      "id": 52,
      "publicId": "Image2_e2gygm",
      "src": "https://res.cloudinary.com/dwerrhasa/image/upload/f_auto,q_auto,w_800/Image2_e2gygm",
      "title": "Image2_e2gygm"
    },
    {
      "id": 53,
      "publicId": "Image5_vvm9gy",
      "src": "https://res.cloudinary.com/dwerrhasa/image/upload/f_auto,q_auto,w_800/Image5_vvm9gy",
      "title": "Image5_vvm9gy"
    },
    {
      "id": 54,
      "publicId": "Image1_btqfyr",
      "src": "https://res.cloudinary.com/dwerrhasa/image/upload/f_auto,q_auto,w_800/Image1_btqfyr",
      "title": "Image1_btqfyr"
    }
  ]
}